nqs_sdk-0.6.9.dist-info/METADATA
nqs_sdk-0.6.9.dist-info/WHEEL
nqs_sdk-0.6.9.dist-info/licenses/LICENSE.txt
nqs_sdk/.gitignore
nqs_sdk/__init__.py
nqs_sdk/bindings/__init__.py
nqs_sdk/bindings/distributions.py
nqs_sdk/bindings/env_builder.py
nqs_sdk/bindings/protocols/__init__.py
nqs_sdk/bindings/protocols/cex/__init__.py
nqs_sdk/bindings/protocols/cex/cex_factory.py
nqs_sdk/bindings/protocols/cex/cex_market.py
nqs_sdk/bindings/protocols/cex/cex_protocol.py
nqs_sdk/bindings/protocols/cex/cex_transactions.py
nqs_sdk/bindings/protocols/protocol_infos.py
nqs_sdk/bindings/protocols/uniswap_v3/__init__.py
nqs_sdk/bindings/protocols/uniswap_v3/spots/__init__.py
nqs_sdk/bindings/protocols/uniswap_v3/spots/historical_uniswap_pool.py
nqs_sdk/bindings/protocols/uniswap_v3/tx_generators/__init__.py
nqs_sdk/bindings/protocols/uniswap_v3/tx_generators/uniswap_v3_historical.py
nqs_sdk/bindings/protocols/uniswap_v3/tx_generators/univswap_v3_random.py
nqs_sdk/bindings/protocols/uniswap_v3/uniswap_utils.py
nqs_sdk/bindings/protocols/uniswap_v3/uniswap_v3_arbitrager.py
nqs_sdk/bindings/protocols/uniswap_v3/uniswap_v3_factory.py
nqs_sdk/bindings/protocols/uniswap_v3/uniswap_v3_pool.py
nqs_sdk/bindings/protocols/uniswap_v3/uniswap_v3_transactions.py
nqs_sdk/bindings/spots/__init__.py
nqs_sdk/bindings/spots/fixed_spot.py
nqs_sdk/bindings/spots/ito_spot.py
nqs_sdk/bindings/spots/spot_generator.py
nqs_sdk/bindings/spots/wgn_spot.py
nqs_sdk/bindings/tx_generators/__init__.py
nqs_sdk/bindings/tx_generators/abstract_transaction.py
nqs_sdk/bindings/tx_generators/historical_tx_generator.py
nqs_sdk/bindings/tx_generators/random_tx_generator.py
nqs_sdk/bindings/utils/__init__.py
nqs_sdk/bindings/utils/utils.py
nqs_sdk/coding_envs/__init__.py
nqs_sdk/coding_envs/coding_env.py
nqs_sdk/coding_envs/policy_caller.py
nqs_sdk/coding_envs/protocols/__init__.py
nqs_sdk/coding_envs/protocols/agent/agent_abstract.py
nqs_sdk/coding_envs/protocols/agent/agent_coding_env.py
nqs_sdk/coding_envs/protocols/cex/cex_abstract.py
nqs_sdk/coding_envs/protocols/cex/cex_coding_env.py
nqs_sdk-0.6.9.dist-info/RECORD
