Metadata-Version: 2.4
Name: nqs_sdk
Version: 0.6.9
Classifier: Development Status :: 3 - Alpha
Classifier: Programming Language :: Python :: 3.12
Classifier: Programming Language :: Python :: 3.13
Classifier: Operating System :: Microsoft :: Windows
Classifier: Operating System :: POSIX :: Linux
Classifier: Operating System :: MacOS
Classifier: Programming Language :: Rust
Requires-Dist: numpy>=1.26.0
Requires-Dist: python-dotenv>=1.0.1
Requires-Dist: dill>=0.3.8
Requires-Dist: sortedcontainers==2.4.0
Requires-Dist: pyyaml==6.0.1
Requires-Dist: restrictedpython>=8.0
Requires-Dist: llm-sandbox[docker]>=0.3.16
Requires-Dist: a2a-sdk>=0.2.11
Requires-Dist: pandas>=2.3.0
License-File: LICENSE.txt
Summary: Nuant Quantitative System SDK
Author: The Lab @ Nuant
Maintainer-email: "The Lab @ Nuant" <thelab@nuant.ai>
Requires-Python: >=3.12, <3.14
Project-URL: homepage, https://github.com/Nuant/nqs-sdk
Project-URL: documentation, https://nuant.github.io/nqs-sdk/
Project-URL: repository, https://github.com/Nuant/nqs-sdk
Project-URL: Changelog, https://github.com/Nuant/nqs-sdk/blob/master/CHANGELOG.md
